llm_bench/__init__.py
llm_bench/check_models.py
llm_bench/check_ollama.py
llm_bench/data/all-large_models.yml
llm_bench/data/all-medium_models.yml
llm_bench/data/all-small_models.yml
llm_bench/data/benchmark_instructions.yml
llm_bench/data/drbx-large_models.yml
llm_bench/data/gemma-medium_models.yml
llm_bench/data/gemma-small_models.yml
llm_bench/data/grok-large_models.yml
llm_bench/data/llama3-large_models.yml
llm_bench/data/llama3-medium_models.yml
llm_bench/data/llama3-small_models.yml
llm_bench/data/mistral-medium_models.yml
llm_bench/data/mistral-small_models.yml
llm_bench/data/phi3-medium_models.yaml
llm_bench/data/phi3-small_models.yml
llm_bench/data/qwen-small_models.yml
llm_bench/data/test_benchmark.yml
llm_bench/data/test_model.yml
llm_bench/main.py
llm_bench/query_llm.py
llm_bench/run_benchmark.py
llm_bench/run_benchmark_one.py
llm_bench/security_connection/__init__.py
llm_bench/security_connection/connection.py
llm_bench/security_connection/security.py
llm_bench/systeminfo/__init__.py
llm_bench/systeminfo/sysmain.py
llm_bench-0.4.32.dist-info/entry_points.txt
llm_bench-0.4.32.dist-info/LICENSE
llm_bench-0.4.32.dist-info/METADATA
llm_bench-0.4.32.dist-info/WHEEL
llm_bench-0.4.32.dist-info/RECORD
