Metadata-Version: 2.1
Name: llm_bench
Version: 0.4.32
Summary: LLM Benchmarking tool for OLLAMA
Home-page: https://github.com/b-Snaas/ollama-benchmark.git
License: MIT
Keywords: benchmark,llama,ollama,llms,local
Author: Snaas
Requires-Python: >=3.8,<4.0
Classifier: License :: OSI Approved :: MIT License
Classifier: Programming Language :: Python :: 3
Classifier: Programming Language :: Python :: 3.8
Classifier: Programming Language :: Python :: 3.9
Classifier: Programming Language :: Python :: 3.10
Classifier: Programming Language :: Python :: 3.11
Classifier: Programming Language :: Python :: 3.12
Requires-Dist: GPUtil (>=1.4.0,<2.0.0)
Requires-Dist: lib-platform (>=1.2.10,<2.0.0)
Requires-Dist: ollama (>=0.1.8,<0.2.0)
Requires-Dist: psutil (>=5.9.8,<6.0.0)
Requires-Dist: pyyaml (>=6.0.1,<7.0.0)
Requires-Dist: requests (>=2.31.0,<3.0.0)
Requires-Dist: setuptools (>=69.1.0,<70.0.0)
Requires-Dist: speedtest-cli (>=2.1.3,<3.0.0)
Requires-Dist: typer[all] (>=0.9.0,<0.10.0)
